Metadata-Version: 1.1
Name: ddns-for-aws
Version: 0.1.0
Summary: Syncs an A Record in Route53 with your external IP
Home-page: https://github.com/aDrongo/ddns-for-aws/
Author: Ben Gardner
Author-email: bgardner160@gmail.com
License: UNKNOWN
Download-URL: https://github.com/aDrongo/ddns-for-aws/archive/0.1.tar.gz
Platform: UNKNOWN
